thinklabs_powerflow/__init__.py
thinklabs_powerflow/cli.py
thinklabs_powerflow/utils.py
thinklabs_powerflow-0.2.3.dist-info/METADATA
thinklabs_powerflow-0.2.3.dist-info/WHEEL
thinklabs_powerflow-0.2.3.dist-info/entry_points.txt
thinklabs_powerflow-0.2.3.dist-info/top_level.txt
thinklabs_powerflow-0.2.3.dist-info/RECORD
