Metadata-Version: 2.1
Name: thinklabs-powerflow
Version: 0.2.3
Summary: A CLI tool to process active and reactive power files and send them for power flow analysis
Home-page: https://github.com/thinklabs-ai/thinklabs-powerflow-package.git
Author: Suren Vallabhajosyula
Author-email: suren.vallabhajosyula@thinklabs.ai
Classifier: Programming Language :: Python :: 3
Classifier: Development Status :: 2 - Pre-Alpha
Classifier: Operating System :: OS Independent
Requires-Python: >=3.12
Requires-Dist: click
Requires-Dist: requests
Requires-Dist: pandas==2.2.3
Requires-Dist: numpy==2.1.2
Requires-Dist: certifi
Requires-Dist: psycopg2-binary
Requires-Dist: boto3
